pyfocas/__init__.py
pyfocas/main.py
pyfocas/protocol/functions.py
pyfocas/protocol/packet.py
pyfocas/protocol/protocol.py
pyfocas-0.1.dist-info/METADATA
pyfocas-0.1.dist-info/WHEEL
pyfocas-0.1.dist-info/entry_points.txt
pyfocas-0.1.dist-info/RECORD
