Metadata-Version: 2.4
Name: pyfocas
Version: 0.1
Summary: A reimplementation of the FOCAS protocol using UNIX sockets.
Keywords: focas,fanuc
Author: Moritz Breurather
Author-email: breurather@ift.at
Requires-Python: >=3.10,<4
Classifier: Programming Language :: Python :: 3
Classifier: Programming Language :: Python :: 3.10
Classifier: Programming Language :: Python :: 3.11
Classifier: Programming Language :: Python :: 3.12
Classifier: Programming Language :: Python :: 3.13
Classifier: Programming Language :: Python :: 3.14
Provides-Extra: dev
Provides-Extra: test
Requires-Dist: Flake8-pyproject (>=1.2.3) ; extra == "dev"
Requires-Dist: mypy (>=1.16.1) ; extra == "dev"
Requires-Dist: pylint (>=3.3.7) ; extra == "dev"
Requires-Dist: pytest (>=8.4.2) ; extra == "test"
